safepi/World.py
safepi/__init__.py
safepi/libs_root.py
safepi/__pycache__/World.cpython-36.pyc
safepi/__pycache__/__init__.cpython-36.pyc
safepi/__pycache__/libs_root.cpython-36.pyc
safepi/libs/Person.cp36-win_amd64.pyd
SafePI-0.0.1a1.dist-info/LICENSE.txt
SafePI-0.0.1a1.dist-info/METADATA
SafePI-0.0.1a1.dist-info/WHEEL
SafePI-0.0.1a1.dist-info/top_level.txt
SafePI-0.0.1a1.dist-info/RECORD
