Metadata-Version: 2.1
Name: SafePI
Version: 0.0.1a1
Summary: A demo PyPi package to demonstrate Python code distribution in a safe and automated way
Home-page: https://github.com/dhchenx/SafePI
Author: Donghua Chen
Author-email: douglaschan@126.com
License: UNKNOWN
Project-URL: Bug Reports, https://github.com/dhchenx/SafePI/issues
Keywords: protect code,rapid software distribution,pyd,cypthon
Platform: UNKNOWN
Classifier: Development Status :: 3 - Alpha
Classifier: Intended Audience :: Developers
Classifier: Topic :: Software Development :: Build Tools
Classifier: License :: OSI Approved :: MIT License
Classifier: Programming Language :: Python :: 3
Classifier: Programming Language :: Python :: 3.6
Classifier: Programming Language :: Python :: 3.7
Classifier: Programming Language :: Python :: 3.8
Classifier: Programming Language :: Python :: 3.9
Classifier: Programming Language :: Python :: 3 :: Only
Requires-Python: >=3.6, <4
License-File: LICENSE.txt
Requires-Dist: Cython
Provides-Extra: dev
Requires-Dist: check-manifest ; extra == 'dev'
Provides-Extra: test
Requires-Dist: coverage ; extra == 'test'
